regioncam-0.5.2.dist-info/METADATA
regioncam-0.5.2.dist-info/WHEEL
regioncam/__init__.py
regioncam/regioncam.abi3.so
regioncam-0.5.2.dist-info/RECORD
