Metadata-Version: 2.4
Name: regioncam
Version: 0.5.2
Requires-Dist: numpy
Summary: Visualize linear regions in neural networks
Author: Twan van Laarhoven <twanvl@gmail.com>
Author-email: Twan van Laarhoven <twanvl@gmail.com>
License: MIT OR Apache-2.0
Project-URL: Source Code, https://github.com/twanvl/regioncam/
